topsis_102203821/__init__.py
topsis_102203821/main.py
topsis_102203821-0.4.dist-info/LICENSE
topsis_102203821-0.4.dist-info/METADATA
topsis_102203821-0.4.dist-info/WHEEL
topsis_102203821-0.4.dist-info/entry_points.txt
topsis_102203821-0.4.dist-info/top_level.txt
topsis_102203821-0.4.dist-info/RECORD
